browserhistory.py
browserhistory-0.1.2.dist-info/LICENSE.txt
browserhistory-0.1.2.dist-info/METADATA
browserhistory-0.1.2.dist-info/WHEEL
browserhistory-0.1.2.dist-info/top_level.txt
browserhistory-0.1.2.dist-info/RECORD
