Metadata-Version: 2.1
Name: browserhistory
Version: 0.1.2
Summary: A simple module to extract browsers's history.
Home-page: https://github.com/kcp18/browserhistory
Author: Chanwoo Park
Author-email: parkchan@brandeis.edu
License: MIT
Platform: Linux
Platform: MacOS
Platform: Windows
Classifier: Programming Language :: Python :: 3.5
Classifier: License :: OSI Approved :: MIT License
Classifier: Operating System :: POSIX :: Linux
Classifier: Operating System :: MacOS
Classifier: Operating System :: Microsoft :: Windows
Classifier: Topic :: Internet :: WWW/HTTP :: Browsers
Classifier: Topic :: Database
